reverse_tb/__init__.py
reverse_tb/_modidx.py
reverse_tb/core.py
reverse_tb/on.py
reverse_tb-0.0.4.dist-info/LICENSE
reverse_tb-0.0.4.dist-info/METADATA
reverse_tb-0.0.4.dist-info/WHEEL
reverse_tb-0.0.4.dist-info/entry_points.txt
reverse_tb-0.0.4.dist-info/top_level.txt
reverse_tb-0.0.4.dist-info/RECORD
