Metadata-Version: 2.1
Name: reverse-tb
Version: 0.0.4
Summary: reverse_tb is a jupyter notebook magic that reverses the order of the traceback, making it easier to see the most relevant information at the top of the cell output.
Home-page: https://github.com/ababino/reverse_tb
Author: Andres Babino
Author-email: ababino@gmail.com
License: Apache Software License 2.0
Keywords: nbdev jupyter notebook python
Classifier: Development Status :: 4 - Beta
Classifier: Intended Audience :: Developers
Classifier: Natural Language :: English
Classifier: Programming Language :: Python :: 3.7
Classifier: Programming Language :: Python :: 3.8
Classifier: Programming Language :: Python :: 3.9
Classifier: Programming Language :: Python :: 3.10
Classifier: License :: OSI Approved :: Apache Software License
Requires-Python: >=3.7
License-File: LICENSE
Requires-Dist: fastcore
Provides-Extra: dev
Requires-Dist: twine ; extra == 'dev'
